jmflashcards/__init__.py
jmflashcards/commands.py
jmflashcards/errors.py
jmflashcards/expression.py
jmflashcards/fcdeluxe.py
jmflashcards/latex.py
jmflashcards/logs.py
jmflashcards/parser.py
jmflashcards/runner.py
jmflashcards/syncronizer.py
jmflashcards/util.py
jmflashcards-0.0.2.data/scripts/jmflashcards
jmflashcards-0.0.2.dist-info/LICENSE
jmflashcards-0.0.2.dist-info/METADATA
jmflashcards-0.0.2.dist-info/WHEEL
jmflashcards-0.0.2.dist-info/top_level.txt
jmflashcards-0.0.2.dist-info/RECORD
