Metadata-Version: 2.1
Name: jmflashcards
Version: 0.0.2
Summary: A Flashcard deluxe flashcard processor
Home-page: https://github.com/llou/jmflashcards
Author: Jorge Monforte González
Author-email: yo@llou.net
License: MiT
Keywords: flashcards latex
Platform: UNKNOWN
Classifier: Environment :: Console
Classifier: Development Status :: 5 - Production/Stable
Classifier: Intended Audience :: Education
Classifier: Intended Audience :: End Users/Desktop
Classifier: Intended Audience :: Developers
Classifier: License :: OSI Approved :: MIT License
Classifier: Natural Language :: English
Classifier: Operating System :: POSIX
Classifier: Programming Language :: Python :: 2.7
Classifier: Topic :: Education :: Computer Aided Instruction (CAI)
Classifier: Topic :: Text Processing
